ics/__init__.py
ics/__version.py
ics/hiddenimports.py
ics/ics.cp312-win_amd64.pyd
ics/py_neo_device_ex.py
ics/structures/__init__.py
ics/structures/a2_b_monitor_settings.py
ics/structures/a2_b_node_type.py
ics/structures/a2_btdm_mode.py
ics/structures/accessory_error_type.py
ics/structures/can_settings.py
ics/structures/canfd_settings.py
ics/structures/canterm_settings.py
ics/structures/clock_quality_.py
ics/structures/cmp_global_data.py
ics/structures/cmp_network_data.py
ics/structures/current_ds_.py
ics/structures/device_feature.py
ics/structures/disk_settings.py
ics/structures/e_dev_name_type.py
ics/structures/e_device_settings_type.py
ics/structures/e_disk_format.py
ics/structures/e_disk_layout.py
ics/structures/e_generic_api_options.py
ics/structures/e_gptp_port.py
ics/structures/e_gptp_profile.py
ics/structures/e_gptp_role.py
ics/structures/e_plasma_ion_vnet_channel_t.py
ics/structures/e_uart_port_t.py
ics/structures/epsilon10_gphyfw.py
ics/structures/epsilon_10_g_phy_select.py
ics/structures/ethernet10_g_settings.py
ics/structures/ethernet10_t1_s_settings.py
ics/structures/ethernet10_t1_s_settings_ext.py
ics/structures/ethernet_network_status_t.py
ics/structures/ethernet_settings.py
ics/structures/ethernet_settings2.py
ics/structures/ew_bms_instance_t.py
ics/structures/ew_bms_manager_lock_state_t.py
ics/structures/ew_bms_manager_port_t.py
ics/structures/extended_response_code.py
ics/structures/extended_response_generic.py
ics/structures/fire3_linux_settings.py
ics/structures/flash_accessory_firmware_params.py
ics/structures/flash_accessory_index.py
ics/structures/flex_vnet_mode.py
ics/structures/generic_api_data.py
ics/structures/generic_api_data_old.py
ics/structures/generic_api_selector.py
ics/structures/generic_api_status.py
ics/structures/generic_binary_status.py
ics/structures/gigastar2_fw_variants.py
ics/structures/global_settings.py
ics/structures/gptp_status.py
ics/structures/ics_device_status.py
ics/structures/ics_fire2_device_status.py
python_ics-921.16.dist-info/licenses/LICENSE.md
python_ics-921.16.dist-info/METADATA
python_ics-921.16.dist-info/WHEEL
python_ics-921.16.dist-info/top_level.txt
python_ics-921.16.dist-info/RECORD
