Metadata-Version: 2.4
Name: python_ics
Version: 921.16
Summary: Python wrapper for interfacing to IntrepidCS Hardware.
Download-URL: https://github.com/intrepidcs/python_ics/releases
Author-email: David Rebbe <drebbe@intrepidcs.com>
Maintainer-email: David Rebbe <drebbe@intrepidcs.com>
License: The MIT License (MIT)
Project-URL: Homepage, https://intrepidcs.com
Project-URL: Documentation, http://python-ics.readthedocs.io/
Project-URL: Repository, https://github.com/intrepidcs/python_ics/
Project-URL: Issues, https://github.com/intrepidcs/python_ics/issues
Keywords: intrepidcs,CAN,Ethernet,Automotive,ICS
Classifier: Development Status :: 5 - Production/Stable
Classifier: Intended Audience :: Developers
Classifier: Operating System :: OS Independent
Classifier: Topic :: Software Development :: Libraries :: Python Modules
Classifier: Programming Language :: Python
Classifier: Programming Language :: Python :: 3
Classifier: Programming Language :: Python :: 3.10
Classifier: Programming Language :: Python :: 3.11
Classifier: Programming Language :: Python :: 3.12
Classifier: Programming Language :: Python :: 3.13
Classifier: Programming Language :: Python :: 3.14
Requires-Python: >=3.10
License-File: LICENSE.md
Dynamic: download-url
Dynamic: license-file
